odoo/addons/web_calendar_slot_duration/README.rst
odoo/addons/web_calendar_slot_duration/__init__.py
odoo/addons/web_calendar_slot_duration/__manifest__.py
odoo/addons/web_calendar_slot_duration/demo/scheduled_actions.xml
odoo/addons/web_calendar_slot_duration/i18n/de.po
odoo/addons/web_calendar_slot_duration/i18n/it.po
odoo/addons/web_calendar_slot_duration/i18n/pt_BR.po
odoo/addons/web_calendar_slot_duration/i18n/web_calendar_slot_duration.pot
odoo/addons/web_calendar_slot_duration/readme/CONFIGURE.md
odoo/addons/web_calendar_slot_duration/readme/CONTRIBUTORS.md
odoo/addons/web_calendar_slot_duration/readme/DESCRIPTION.md
odoo/addons/web_calendar_slot_duration/readme/ROADMAP.md
odoo/addons/web_calendar_slot_duration/readme/USAGE.md
odoo/addons/web_calendar_slot_duration/static/description/calendar_result.png
odoo/addons/web_calendar_slot_duration/static/description/edit_action.png
odoo/addons/web_calendar_slot_duration/static/description/icon.png
odoo/addons/web_calendar_slot_duration/static/description/index.html
odoo/addons/web_calendar_slot_duration/static/src/js/calendar_common_renderer.esm.js
odoo/addons/web_calendar_slot_duration/static/src/js/calendar_model.esm.js
odoo_addon_web_calendar_slot_duration-18.0.1.0.0.2.dist-info/METADATA
odoo_addon_web_calendar_slot_duration-18.0.1.0.0.2.dist-info/WHEEL
odoo_addon_web_calendar_slot_duration-18.0.1.0.0.2.dist-info/top_level.txt
odoo_addon_web_calendar_slot_duration-18.0.1.0.0.2.dist-info/RECORD
